awslabs/__init__.py
awslabs/amazon_kendra_index_mcp_server/__init__.py
awslabs/amazon_kendra_index_mcp_server/server.py
awslabs/amazon_kendra_index_mcp_server/util.py
awslabs_amazon_kendra_index_mcp_server-1.0.11.dist-info/METADATA
awslabs_amazon_kendra_index_mcp_server-1.0.11.dist-info/WHEEL
awslabs_amazon_kendra_index_mcp_server-1.0.11.dist-info/entry_points.txt
awslabs_amazon_kendra_index_mcp_server-1.0.11.dist-info/licenses/LICENSE
awslabs_amazon_kendra_index_mcp_server-1.0.11.dist-info/licenses/NOTICE
awslabs_amazon_kendra_index_mcp_server-1.0.11.dist-info/RECORD
